setup.py
grpc/__init__.py
grpc/gevent_profiler.py
grpc/rpc.py
grpc/rpc_shell.py
grpc.egg-info/PKG-INFO
grpc.egg-info/SOURCES.txt
grpc.egg-info/dependency_links.txt
grpc.egg-info/top_level.txt
grpc/test/client.py
grpc/test/server.py
grpc/test/shell.py