Metadata-Version: 1.0
Name: grpc
Version: 0.3-13
Summary: Pure Python Gevent RPC
